[{"phase":"NEW","time":"1927-01-04T01:28:00.000Z"},{"phase":"FIRST","time":"1927-01-10T19:43:00.000Z"},{"phase":"FULL","time":"1927-01-18T03:27:00.000Z"},{"phase":"LAST","time":"1927-01-26T07:05:00.000Z"},{"phase":"NEW","time":"1927-02-02T13:54:00.000Z"},{"phase":"FIRST","time":"1927-02-09T04:54:00.000Z"},{"phase":"FULL","time":"1927-02-16T21:18:00.000Z"},{"phase":"LAST","time":"1927-02-25T01:42:00.000Z"},{"phase":"NEW","time":"1927-03-04T00:25:00.000Z"},{"phase":"FIRST","time":"1927-03-10T16:03:00.000Z"},{"phase":"FULL","time":"1927-03-18T15:24:00.000Z"},{"phase":"LAST","time":"1927-03-26T16:35:00.000Z"},{"phase":"NEW","time":"1927-04-02T09:24:00.000Z"},{"phase":"FIRST","time":"1927-04-09T05:21:00.000Z"},{"phase":"FULL","time":"1927-04-17T08:35:00.000Z"},{"phase":"LAST","time":"1927-04-25T02:21:00.000Z"},{"phase":"NEW","time":"1927-05-01T16:40:00.000Z"},{"phase":"FIRST","time":"1927-05-08T19:27:00.000Z"},{"phase":"FULL","time":"1927-05-16T23:03:00.000Z"},{"phase":"LAST","time":"1927-05-24T09:34:00.000Z"},{"phase":"NEW","time":"1927-05-31T01:06:00.000Z"},{"phase":"FIRST","time":"1927-06-07T11:49:00.000Z"},{"phase":"FULL","time":"1927-06-15T12:19:00.000Z"},{"phase":"LAST","time":"1927-06-22T14:29:00.000Z"},{"phase":"NEW","time":"1927-06-29T10:32:00.000Z"},{"phase":"FIRST","time":"1927-07-07T04:52:00.000Z"},{"phase":"FULL","time":"1927-07-14T23:22:00.000Z"},{"phase":"LAST","time":"1927-07-21T18:43:00.000Z"},{"phase":"NEW","time":"1927-07-28T21:36:00.000Z"},{"phase":"FIRST","time":"1927-08-05T22:05:00.000Z"},{"phase":"FULL","time":"1927-08-13T08:37:00.000Z"},{"phase":"LAST","time":"1927-08-19T23:54:00.000Z"},{"phase":"NEW","time":"1927-08-27T10:45:00.000Z"},{"phase":"FIRST","time":"1927-09-04T14:44:00.000Z"},{"phase":"FULL","time":"1927-09-11T16:54:00.000Z"},{"phase":"LAST","time":"1927-09-18T07:29:00.000Z"},{"phase":"NEW","time":"1927-09-26T03:11:00.000Z"},{"phase":"FIRST","time":"1927-10-04T07:02:00.000Z"},{"phase":"FULL","time":"1927-10-11T02:15:00.000Z"},{"phase":"LAST","time":"1927-10-17T19:32:00.000Z"},{"phase":"NEW","time":"1927-10-25T20:37:00.000Z"},{"phase":"FIRST","time":"1927-11-02T20:16:00.000Z"},{"phase":"FULL","time":"1927-11-09T11:36:00.000Z"},{"phase":"LAST","time":"1927-11-16T10:28:00.000Z"},{"phase":"NEW","time":"1927-11-24T15:09:00.000Z"},{"phase":"FIRST","time":"1927-12-02T07:15:00.000Z"},{"phase":"FULL","time":"1927-12-08T22:32:00.000Z"},{"phase":"LAST","time":"1927-12-16T05:04:00.000Z"},{"phase":"NEW","time":"1927-12-24T09:13:00.000Z"},{"phase":"FIRST","time":"1927-12-31T16:22:00.000Z"}]