[{"phase":"FIRST","time":"2058-01-01T23:30:00.000Z"},{"phase":"FULL","time":"2058-01-10T01:39:00.000Z"},{"phase":"LAST","time":"2058-01-18T00:43:00.000Z"},{"phase":"NEW","time":"2058-01-24T17:14:00.000Z"},{"phase":"FIRST","time":"2058-01-31T15:28:00.000Z"},{"phase":"FULL","time":"2058-02-08T20:54:00.000Z"},{"phase":"LAST","time":"2058-02-16T12:16:00.000Z"},{"phase":"NEW","time":"2058-02-23T03:57:00.000Z"},{"phase":"FIRST","time":"2058-03-02T10:10:00.000Z"},{"phase":"FULL","time":"2058-03-10T12:53:00.000Z"},{"phase":"LAST","time":"2058-03-17T19:56:00.000Z"},{"phase":"NEW","time":"2058-03-24T13:50:00.000Z"},{"phase":"FIRST","time":"2058-04-01T05:03:00.000Z"},{"phase":"FULL","time":"2058-04-09T02:55:00.000Z"},{"phase":"LAST","time":"2058-04-16T02:27:00.000Z"},{"phase":"NEW","time":"2058-04-23T01:29:00.000Z"},{"phase":"FIRST","time":"2058-05-01T00:18:00.000Z"},{"phase":"FULL","time":"2058-05-08T14:12:00.000Z"},{"phase":"LAST","time":"2058-05-15T07:58:00.000Z"},{"phase":"NEW","time":"2058-05-22T14:23:00.000Z"},{"phase":"FIRST","time":"2058-05-30T17:33:00.000Z"},{"phase":"FULL","time":"2058-06-06T23:15:00.000Z"},{"phase":"LAST","time":"2058-06-13T13:51:00.000Z"},{"phase":"NEW","time":"2058-06-21T04:35:00.000Z"},{"phase":"FIRST","time":"2058-06-29T08:13:00.000Z"},{"phase":"FULL","time":"2058-07-06T06:47:00.000Z"},{"phase":"LAST","time":"2058-07-12T21:28:00.000Z"},{"phase":"NEW","time":"2058-07-20T19:40:00.000Z"},{"phase":"FIRST","time":"2058-07-28T20:19:00.000Z"},{"phase":"FULL","time":"2058-08-04T13:38:00.000Z"},{"phase":"LAST","time":"2058-08-11T08:00:00.000Z"},{"phase":"NEW","time":"2058-08-19T11:03:00.000Z"},{"phase":"FIRST","time":"2058-08-27T06:10:00.000Z"},{"phase":"FULL","time":"2058-09-02T20:51:00.000Z"},{"phase":"LAST","time":"2058-09-09T22:07:00.000Z"},{"phase":"NEW","time":"2058-09-18T02:18:00.000Z"},{"phase":"FIRST","time":"2058-09-25T14:14:00.000Z"},{"phase":"FULL","time":"2058-10-02T05:36:00.000Z"},{"phase":"LAST","time":"2058-10-09T15:41:00.000Z"},{"phase":"NEW","time":"2058-10-17T17:05:00.000Z"},{"phase":"FIRST","time":"2058-10-24T21:16:00.000Z"},{"phase":"FULL","time":"2058-10-31T16:54:00.000Z"},{"phase":"LAST","time":"2058-11-08T12:47:00.000Z"},{"phase":"NEW","time":"2058-11-16T08:09:00.000Z"},{"phase":"FIRST","time":"2058-11-23T05:16:00.000Z"},{"phase":"FULL","time":"2058-11-30T08:17:00.000Z"},{"phase":"LAST","time":"2058-12-08T09:51:00.000Z"},{"phase":"NEW","time":"2058-12-15T21:12:00.000Z"},{"phase":"FIRST","time":"2058-12-22T13:27:00.000Z"},{"phase":"FULL","time":"2058-12-30T01:25:00.000Z"}]