[{"day":6,"month":1,"phase":0,"time":"07:24","year":1981},{"day":20,"month":1,"phase":2,"time":"07:39","year":1981},{"day":28,"month":1,"phase":3,"time":"04:19","year":1981},{"day":4,"month":2,"phase":0,"time":"22:14","year":1981},{"day":18,"month":2,"phase":2,"time":"22:58","year":1981},{"day":27,"month":2,"phase":3,"time":"01:14","year":1981},{"day":6,"month":3,"phase":0,"time":"10:31","year":1981},{"day":20,"month":3,"phase":2,"time":"15:23","year":1981},{"day":28,"month":3,"phase":3,"time":"19:34","year":1981},{"day":4,"month":4,"phase":0,"time":"20:19","year":1981},{"day":19,"month":4,"phase":2,"time":"07:59","year":1981},{"day":27,"month":4,"phase":3,"time":"10:14","year":1981},{"day":4,"month":5,"phase":0,"time":"04:19","year":1981},{"day":19,"month":5,"phase":2,"time":"00:04","year":1981},{"day":26,"month":5,"phase":3,"time":"21:00","year":1981},{"day":2,"month":6,"phase":0,"time":"11:32","year":1981},{"day":17,"month":6,"phase":2,"time":"15:04","year":1981},{"day":25,"month":6,"phase":3,"time":"04:25","year":1981},{"day":1,"month":7,"phase":0,"time":"19:03","year":1981},{"day":17,"month":7,"phase":2,"time":"04:39","year":1981},{"day":24,"month":7,"phase":3,"time":"09:40","year":1981},{"day":31,"month":7,"phase":0,"time":"03:52","year":1981},{"day":15,"month":8,"phase":2,"time":"16:37","year":1981},{"day":22,"month":8,"phase":3,"time":"14:16","year":1981},{"day":29,"month":8,"phase":0,"time":"14:43","year":1981},{"day":14,"month":9,"phase":2,"time":"03:09","year":1981},{"day":20,"month":9,"phase":3,"time":"19:47","year":1981},{"day":28,"month":9,"phase":0,"time":"04:07","year":1981},{"day":13,"month":10,"phase":2,"time":"12:49","year":1981},{"day":20,"month":10,"phase":3,"time":"03:41","year":1981},{"day":27,"month":10,"phase":0,"time":"20:13","year":1981},{"day":11,"month":11,"phase":2,"time":"22:27","year":1981},{"day":18,"month":11,"phase":3,"time":"14:54","year":1981},{"day":26,"month":11,"phase":0,"time":"14:38","year":1981},{"day":11,"month":12,"phase":2,"time":"08:41","year":1981},{"day":18,"month":12,"phase":3,"time":"05:47","year":1981},{"day":26,"month":12,"phase":0,"time":"10:10","year":1981}]