[{"phase":"NEW","time":"2038-01-05T18:41:00.000Z"},{"phase":"FIRST","time":"2038-01-13T17:34:00.000Z"},{"phase":"FULL","time":"2038-01-21T09:00:00.000Z"},{"phase":"LAST","time":"2038-01-28T03:00:00.000Z"},{"phase":"NEW","time":"2038-02-04T10:52:00.000Z"},{"phase":"FIRST","time":"2038-02-12T14:30:00.000Z"},{"phase":"FULL","time":"2038-02-19T21:09:00.000Z"},{"phase":"LAST","time":"2038-02-26T11:56:00.000Z"},{"phase":"NEW","time":"2038-03-06T04:15:00.000Z"},{"phase":"FIRST","time":"2038-03-14T07:41:00.000Z"},{"phase":"FULL","time":"2038-03-21T06:09:00.000Z"},{"phase":"LAST","time":"2038-03-27T21:36:00.000Z"},{"phase":"NEW","time":"2038-04-04T20:43:00.000Z"},{"phase":"FIRST","time":"2038-04-12T22:02:00.000Z"},{"phase":"FULL","time":"2038-04-19T14:36:00.000Z"},{"phase":"LAST","time":"2038-04-26T10:15:00.000Z"},{"phase":"NEW","time":"2038-05-04T13:19:00.000Z"},{"phase":"FIRST","time":"2038-05-12T08:18:00.000Z"},{"phase":"FULL","time":"2038-05-18T22:23:00.000Z"},{"phase":"LAST","time":"2038-05-26T00:43:00.000Z"},{"phase":"NEW","time":"2038-06-03T04:24:00.000Z"},{"phase":"FIRST","time":"2038-06-10T15:11:00.000Z"},{"phase":"FULL","time":"2038-06-17T06:30:00.000Z"},{"phase":"LAST","time":"2038-06-24T16:39:00.000Z"},{"phase":"NEW","time":"2038-07-02T17:32:00.000Z"},{"phase":"FIRST","time":"2038-07-09T20:00:00.000Z"},{"phase":"FULL","time":"2038-07-16T15:48:00.000Z"},{"phase":"LAST","time":"2038-07-24T09:40:00.000Z"},{"phase":"NEW","time":"2038-08-01T04:40:00.000Z"},{"phase":"FIRST","time":"2038-08-08T00:21:00.000Z"},{"phase":"FULL","time":"2038-08-15T02:57:00.000Z"},{"phase":"LAST","time":"2038-08-23T03:12:00.000Z"},{"phase":"NEW","time":"2038-08-30T14:13:00.000Z"},{"phase":"FIRST","time":"2038-09-06T05:51:00.000Z"},{"phase":"FULL","time":"2038-09-13T16:24:00.000Z"},{"phase":"LAST","time":"2038-09-21T20:27:00.000Z"},{"phase":"NEW","time":"2038-09-28T22:57:00.000Z"},{"phase":"FIRST","time":"2038-10-05T13:52:00.000Z"},{"phase":"FULL","time":"2038-10-13T08:22:00.000Z"},{"phase":"LAST","time":"2038-10-21T12:23:00.000Z"},{"phase":"NEW","time":"2038-10-28T07:53:00.000Z"},{"phase":"FIRST","time":"2038-11-04T01:23:00.000Z"},{"phase":"FULL","time":"2038-11-12T03:27:00.000Z"},{"phase":"LAST","time":"2038-11-20T03:10:00.000Z"},{"phase":"NEW","time":"2038-11-26T18:46:00.000Z"},{"phase":"FIRST","time":"2038-12-03T17:46:00.000Z"},{"phase":"FULL","time":"2038-12-11T22:30:00.000Z"},{"phase":"LAST","time":"2038-12-19T14:29:00.000Z"},{"phase":"NEW","time":"2038-12-26T06:02:00.000Z"}]